cheapi/__init__.py
cheapi/wrapper.py
cheapi-0.1.0.dist-info/WHEEL
cheapi-0.1.0.dist-info/METADATA
cheapi-0.1.0.dist-info/RECORD
