Metadata-Version: 2.1
Name: cheapi
Version: 0.1.0
Summary: Make API usage cheap! Caching wrapper for third party APIs.
Author: Arseny Kravchenko
Author-email: me@arseny.info
Requires-Python: >=3.8,<4.0
Classifier: Programming Language :: Python :: 3
Classifier: Programming Language :: Python :: 3.8
Classifier: Programming Language :: Python :: 3.9
Classifier: Programming Language :: Python :: 3.10
Classifier: Programming Language :: Python :: 3.11
